mcp_server_gcodeclean/__init__.py
mcp_server_gcodeclean/py.typed
mcp_server_gcodeclean/server.py
mcp_server_gcodeclean/resources/gcodeclean/version.json
mcp_server_gcodeclean/resources/gcodeclean/1.4.2/LICENSE
mcp_server_gcodeclean/resources/gcodeclean/1.4.2/linux-arm/GCC
mcp_server_gcodeclean/resources/gcodeclean/1.4.2/linux-arm/GCC.pdb
mcp_server_gcodeclean/resources/gcodeclean/1.4.2/linux-arm/GCodeClean.pdb
mcp_server_gcodeclean/resources/gcodeclean/1.4.2/linux-arm/tokenDefinitions.json
mcp_server_gcodeclean/resources/gcodeclean/1.4.2/linux-x64/GCC
mcp_server_gcodeclean/resources/gcodeclean/1.4.2/linux-x64/GCC.pdb
mcp_server_gcodeclean/resources/gcodeclean/1.4.2/linux-x64/GCodeClean.pdb
mcp_server_gcodeclean/resources/gcodeclean/1.4.2/linux-x64/tokenDefinitions.json
mcp_server_gcodeclean/resources/gcodeclean/1.4.2/osx-arm64/GCC
mcp_server_gcodeclean/resources/gcodeclean/1.4.2/osx-arm64/GCC.pdb
mcp_server_gcodeclean/resources/gcodeclean/1.4.2/osx-arm64/tokenDefinitions.json
mcp_server_gcodeclean/resources/gcodeclean/1.4.2/osx-x64/GCC
mcp_server_gcodeclean/resources/gcodeclean/1.4.2/osx-x64/GCC.pdb
mcp_server_gcodeclean/resources/gcodeclean/1.4.2/osx-x64/tokenDefinitions.json
mcp_server_gcodeclean/resources/gcodeclean/1.4.2/win-x64/GCC.exe
mcp_server_gcodeclean/resources/gcodeclean/1.4.2/win-x64/GCC.pdb
mcp_server_gcodeclean/resources/gcodeclean/1.4.2/win-x64/GCodeClean.pdb
mcp_server_gcodeclean/resources/gcodeclean/1.4.2/win-x64/tokenDefinitions.json
mcp_server_gcodeclean-0.2.0.dist-info/METADATA
mcp_server_gcodeclean-0.2.0.dist-info/WHEEL
mcp_server_gcodeclean-0.2.0.dist-info/entry_points.txt
mcp_server_gcodeclean-0.2.0.dist-info/licenses/LICENSE
mcp_server_gcodeclean-0.2.0.dist-info/RECORD
