Metadata-Version: 2.4
Name: mcp-server-gcodeclean
Version: 0.2.0
Summary: MCP server for G-code syntax validation using GCodeClean
Project-URL: Homepage, https://github.com/ivan-loh/mcp-server-gcodeclean
Project-URL: Repository, https://github.com/ivan-loh/mcp-server-gcodeclean
Project-URL: Issues, https://github.com/ivan-loh/mcp-server-gcodeclean/issues
Author-email: ivan <ivan@eriad.com>
License: AGPL-3.0
License-File: LICENSE
Keywords: cnc,gcode,manufacturing,mcp,validation
Classifier: Development Status :: 4 - Beta
Classifier: Intended Audience :: Developers
Classifier: Intended Audience :: Manufacturing
Classifier: License :: OSI Approved :: GNU Affero General Public License v3
Classifier: Operating System :: OS Independent
Classifier: Programming Language :: Python :: 3
Classifier: Programming Language :: Python :: 3.10
Classifier: Programming Language :: Python :: 3.11
Classifier: Programming Language :: Python :: 3.12
Classifier: Topic :: Scientific/Engineering
Classifier: Topic :: Software Development :: Quality Assurance
Requires-Python: >=3.10
Requires-Dist: fastmcp>=0.4.0
